License.txt
MANIFEST.in
README.md
setup.py
fftw/fftw3.h
fftw/win32/libfftw3-3.def
fftw/win32/libfftw3-3.dll
fftw/win32/libfftw3-3.exp
fftw/win32/libfftw3f-3.def
fftw/win32/libfftw3f-3.dll
fftw/win32/libfftw3f-3.exp
fftw/win32/libfftw3l-3.def
fftw/win32/libfftw3l-3.dll
fftw/win32/libfftw3l-3.exp
fftw/win64/libfftw3-3.def
fftw/win64/libfftw3-3.dll
fftw/win64/libfftw3-3.exp
fftw/win64/libfftw3f-3.def
fftw/win64/libfftw3f-3.dll
fftw/win64/libfftw3f-3.exp
fftw/win64/libfftw3l-3.def
fftw/win64/libfftw3l-3.dll
fftw/win64/libfftw3l-3.exp
pyqstem/QSTEM.cpp
pyqstem/QSTEM.h
pyqstem/__init__.py
pyqstem/detection.py
pyqstem/imaging.py
pyqstem/potentials.py
pyqstem/qstem_interface.cpp
pyqstem/qstem_interface.pyx
pyqstem/thermal.py
pyqstem/util.py
pyqstem/wave.py
pyqstem.egg-info/PKG-INFO
pyqstem.egg-info/SOURCES.txt
pyqstem.egg-info/dependency_links.txt
pyqstem.egg-info/requires.txt
pyqstem.egg-info/top_level.txt
source/data_containers.cpp
source/data_containers.h
source/fileio_fftw3.cpp
source/fileio_fftw3.h
source/imagelib_fftw3.cpp
source/imagelib_fftw3.h
source/matrixlib.cpp
source/matrixlib.h
source/memory_fftw3.cpp
source/memory_fftw3.h
source/readparams.cpp
source/readparams.h
source/scatfactsRez.h
source/stemlib.cpp
source/stemlib.h
source/stemtypes_fftw3.h
source/stemutil.cpp
source/stemutil.h
test/test_CBED.py
test/test_stem.py
test/test_stem_dft.py
test/test_tem.py
test/test_tem_dft.py