Metadata-Version: 1.2
Name: pyqstem
Version: 1.0.3
Summary: A Python interface to the electron microscopy simulation program QSTEM.
Home-page: https://github.com/jacobjma/PyQSTEM
Maintainer: Jacob Madsen
Maintainer-email: jacob.jma@gmail.com
License: GPLv3
Platform: Windows
Platform: Linux
Platform: Mac OS-X
Platform: Unix
